humiologging/__init__.py
humiologging/formatters.py
humiologging/utils.py
humiologging/handlers/__init__.py
humiologging/handlers/base.py
humiologging/handlers/django.py
humiologging-1.0.4.dist-info/LICENSE
humiologging-1.0.4.dist-info/WHEEL
humiologging-1.0.4.dist-info/METADATA
humiologging-1.0.4.dist-info/RECORD
