Metadata-Version: 2.1
Name: humiologging
Version: 1.0.4
Summary: Log utilities for Humio: Handlers, formatters
Author-email: Uninett Opensource <opensource@uninett.no>
Requires-Python: >=3.7
Classifier: Development Status :: 5 - Production/Stable
Classifier: Intended Audience :: Developers
Classifier: Intended Audience :: Information Technology
Classifier: Intended Audience :: System Administrators
Classifier: License :: OSI Approved :: Apache Software License
Classifier: Programming Language :: Python :: 3 :: Only
Classifier: Programming Language :: Python :: 3.7
Classifier: Programming Language :: Python :: 3.8
Classifier: Programming Language :: Python :: 3.9
Classifier: Programming Language :: Python :: 3.10
Classifier: Programming Language :: Python :: 3.11
Classifier: Topic :: System :: Logging
Classifier: Topic :: System :: Monitoring
Requires-Dist: humiolib
Project-URL: Homepage, https://github.com/Uninett/python-logging-humio
